{
    "LIVERPOOL FC": "WWWWDWDWWDWW",
    "NOTTINGHAM FOREST FC": "WWDDWLLWWWWL",
    "ARSENAL FC": "WWDLLDWDWWDW",
    "NEWCASTLE UNITED FC": "DWLDLWDLWWWW",
    "CHELSEA FC": "WWWLDWWWDLDL",
    "FULHAM FC": "LDWLDWDDWLWW",
    "BRIGHTON & HOVE ALBION FC": "WDLWLWLDDDWWL",
    "AFC BOURNEMOUTH": "DWLLDLWWWDDW",
    "CRYSTAL PALACE FC": "LDLLDDWWDWWW",
    "MANCHESTER CITY FC": "WWDWLLLDLWDWL",
    "ASTON VILLA FC": "WWDWLLLLLWDL",
    "TOTTENHAM HOTSPUR FC": "DLWLLWLWLLLW",
    "MANCHESTER UNITED FC": "LWDDLDLWLDW",
    "WEST HAM UNITED FC": "WDDLLWLDWLDL",
    "EVERTON FC": "LLDWLDLDDLW",
    "WOLVERHAMPTON WANDERERS FC": "LDLLDWLLWDLL",
    "IPSWICH TOWN FC": "LDDLLWLWLDL",
    "LEICESTER CITY FC": "LDLWDLLLLLWL",
    "BRENTFORD FC": "LLLLLDLLDWW",
    "SOUTHAMPTON FC": "LLLLLLDLDLLLW"
}