{
    "LEEDS UNITED FC": "DWLWWWWWWWWWDWW",
    "SHEFFIELD UNITED FC": "DWWWWWWWWWLDW",
    "SUNDERLAND AFC": "WWWWDWDDWDWWW",
    "WATFORD FC": "WWDWWWWWDWWLLL",
    "OXFORD UNITED FC": "WWWDDDLWLDLWWWW",
    "BLACKBURN ROVERS FC": "WWWWWDLLWWDLLWL",
    "MIDDLESBROUGH FC": "WDDWLWLWLWWDDDW",
    "BURNLEY FC": "WDWWDDWWDDWDD",
    "BRISTOL CITY FC": "WDWDDDLLWDWWW",
    "NORWICH CITY FC": "DDWDWDLWWLWDW",
    "PRESTON NORTH END FC": "LWDWWDLDDDDWWD",
    "LUTON TOWN FC": "LLWDWLDWWDWWLD",
    "PORTSMOUTH FC": "DLLDDLWWDWWWW",
    "WEST BROMWICH ALBION FC": "DWWLDDDDDWWWD",
    "MILLWALL FC": "LWLWDWWWDLLWLLD",
    "SHEFFIELD WEDNESDAY FC": "WLDWLDLWDDLWWDD",
    "COVENTRY CITY FC": "WLLWLWLDDWWDW",
    "QUEENS PARK RANGERS FC": "LDDLLDDLDWWWWW",
    "DERBY COUNTY FC": "WWWLWDDLLWWLLL",
    "SWANSEA CITY AFC": "WDWDDLWLDLWWDL",
    "STOKE CITY FC": "WLLWDDWDDLDLWD",
    "PLYMOUTH ARGYLE FC": "DLWWWDWDLDDDLL",
    "CARDIFF CITY FC": "LLLWWWWLLLLDDW",
    "HULL CITY AFC": "DDLWLDDLLLDWLDL"
}